trackplot/__init__.py
trackplot/cli.py
trackplot/plot.py
trackplot/plot_func.py
trackplot/plot_tests.py
trackplot/server.py
trackplot/anno/AxLabel.py
trackplot/anno/__init__.py
trackplot/anno/theme.py
trackplot/base/CoordinateMap.py
trackplot/base/GenomicLoci.py
trackplot/base/Junction.py
trackplot/base/Protein.py
trackplot/base/ReadDepth.py
trackplot/base/Readder.py
trackplot/base/Stroke.py
trackplot/base/Transcript.py
trackplot/base/__init__.py
trackplot/base/pyUniprot.py
trackplot/conf/DomainSetting.py
trackplot/conf/__init__.py
trackplot/conf/config.py
trackplot/conf/drawing.py
trackplot/conf/ui.py
trackplot/file/ATAC.py
trackplot/file/Annotation.py
trackplot/file/Bam.py
trackplot/file/BedGraph.py
trackplot/file/Bigwig.py
trackplot/file/Depth.py
trackplot/file/Fasta.py
trackplot/file/File.py
trackplot/file/HiCMatrixTrack.py
trackplot/file/Junction.py
trackplot/file/Motif.py
trackplot/file/ReadSegments.py
trackplot/file/__init__.py
trackplot-0.5.7.dist-info/licenses/LICENSE
ui/index.html
ui/vite.svg
ui/assets/Home-7GzAh8lS.js
ui/assets/Home-BV58jH3t.js
ui/assets/Home-CDW3Zwoa.js
ui/assets/Home-DOO13BH7.js
ui/assets/Home-DZ_TnNqV.js
ui/assets/Home-QmeAKOl4.js
ui/assets/Home-RdVPWns6.js
ui/assets/Home-jSR0MsHI.css
ui/assets/Home-zRV7yePL.css
ui/assets/Plot-BALbchCV.css
ui/assets/Plot-BmqHZ4QE.css
ui/assets/Plot-BrjU8Kwg.js
ui/assets/Plot-Bvyo6ju9.css
ui/assets/Plot-C4RNyMVn.css
ui/assets/Plot-COvGnprQ.css
ui/assets/Plot-CTM-EDrj.js
ui/assets/Plot-Ch3Psf3q.js
ui/assets/Plot-Cnt8iJB8.js
ui/assets/Plot-Cyj_LlDt.js
ui/assets/Plot-DiuFnwNK.js
ui/assets/Plot-DpL7z7tp.css
ui/assets/Plot-hvkDteAn.js
ui/assets/Plot-rbQz1TOM.css
ui/assets/el-divider-BHm65SRq.css
ui/assets/el-divider-BVZhQIwQ.js
ui/assets/el-divider-Brt4-Qvr.js
ui/assets/el-divider-BuEUMHwE.css
ui/assets/el-divider-C8ttpjuy.css
ui/assets/el-divider-Cwxg0Ado.css
ui/assets/el-divider-DcvrsrBa.css
ui/assets/el-divider-DnCOJT55.js
ui/assets/el-divider-IbBQ8ZK2.js
ui/assets/el-divider-SYT5K-ds.css
ui/assets/el-divider-VYjL3C7L.js
trackplot-0.5.7.dist-info/METADATA
trackplot-0.5.7.dist-info/WHEEL
trackplot-0.5.7.dist-info/top_level.txt
trackplot-0.5.7.dist-info/RECORD
