Metadata-Version: 2.4
Name: trackplot
Version: 0.5.7
Summary: The trackplot is a tool for visualizing various next-generation sequencing (NGS) data, including DNA-seq, RNA-seq, single-cell RNA-seq and full-length sequencing datasets. https://sashimi.readthedocs.io/
Author-email: ygidtu <ygidtu@gmail.com>
License-Expression: BSD-3-Clause
Requires-Python: >=3.11
License-File: LICENSE
Requires-Dist: adjusttext>=1.3.0
Requires-Dist: cairocffi>=1.7.1
Requires-Dist: click>=8.2.1
Requires-Dist: click-option-group>=0.5.7
Requires-Dist: filetype>=1.2.0
Requires-Dist: flask>=3.1.1
Requires-Dist: hicmatrix>=17.2
Requires-Dist: loguru>=0.7.3
Requires-Dist: matplotlib>=3.10.3
Requires-Dist: numpy>=2.3.0
Requires-Dist: pandas>=2.3.0
Requires-Dist: pybigwig>=0.3.24
Requires-Dist: pysam>=0.23.3
Requires-Dist: requests>=2.32.4
Requires-Dist: scipy>=1.15.3
Requires-Dist: seaborn>=0.13.2
Requires-Dist: xmltodict>=0.15.0
Dynamic: license-file
